{"2021-01-23": {"total_deceased": "21", "recovered": "0", "total_recovered": "183", "deceased": "0", "total_confirmed": "509", "active": "305", "confirmed": "0"}, "2021-01-22": {"confirmed": "0", "total_recovered": "183", "total_deceased": "21", "recovered": "0", "active": "305", "deceased": "0", "total_confirmed": "509"}, "2021-01-21": {"total_confirmed": "509", "total_deceased": "21", "recovered": "0", "active": "305", "deceased": "0", "total_recovered": "183", "confirmed": "0"}, "2021-01-20": {"total_confirmed": "509", "active": "305", "confirmed": "0", "deceased": "0", "recovered": "0", "total_deceased": "21", "total_recovered": "183"}, "2021-01-19": {"active": "305", "deceased": "0", "confirmed": "0", "recovered": "0", "total_confirmed": "509", "total_recovered": "183", "total_deceased": "21"}, "2021-01-18": {"total_recovered": "183", "total_deceased": "21", "recovered": "0", "total_confirmed": "509", "confirmed": "0", "deceased": "0", "active": "305"}, "2021-01-17": {"recovered": "0", "total_deceased": "21", "total_confirmed": "509", "total_recovered": "183", "confirmed": "0", "deceased": "0", "active": "305"}, "2021-01-16": {"confirmed": "0", "total_deceased": "21", "active": "305", "recovered": "0", "total_recovered": "183", "total_confirmed": "509", "deceased": "0"}, "2021-01-15": {"active": "305", "total_recovered": "183", "recovered": "0", "total_confirmed": "509", "confirmed": "0", "total_deceased": "21", "deceased": "0"}, "2021-01-14": {"total_recovered": "183", "confirmed": "0", "deceased": "0", "total_confirmed": "509", "recovered": "0", "active": "305", "total_deceased": "21"}, "2021-01-13": {"total_deceased": "21", "recovered": "0", "active": "305", "total_recovered": "183", "total_confirmed": "509", "confirmed": "0", "deceased": "0"}, "2021-01-12": {"confirmed": "0", "recovered": "0", "deceased": "0", "active": "305", "total_deceased": "21", "total_recovered": "183", "total_confirmed": "509"}, "2021-01-11": {"total_deceased": "21", "total_recovered": "183", "active": "305", "deceased": "0", "confirmed": "0", "total_confirmed": "509", "recovered": "0"}, "2021-01-10": {"total_recovered": "183", "total_deceased": "21", "active": "305", "recovered": "0", "confirmed": "0", "total_confirmed": "509", "deceased": "0"}, "2021-01-09": {"confirmed": "0", "deceased": "0", "total_deceased": "21", "recovered": "0", "active": "305", "total_confirmed": "509", "total_recovered": "183"}, "2021-01-08": {"recovered": "0", "deceased": "0", "active": "305", "total_recovered": "183", "confirmed": "0", "total_deceased": "21", "total_confirmed": "509"}, "2021-01-07": {"active": "305", "total_deceased": "21", "recovered": "0", "total_confirmed": "509", "confirmed": "0", "deceased": "0", "total_recovered": "183"}, "2021-01-06": {"confirmed": "0", "active": "305", "total_recovered": "183", "deceased": "0", "total_confirmed": "509", "total_deceased": "21", "recovered": "0"}, "2021-01-05": {"active": "305", "total_recovered": "183", "confirmed": "0", "deceased": "0", "total_confirmed": "509", "recovered": "0", "total_deceased": "21"}, "2021-01-04": {"total_confirmed": "509", "confirmed": "0", "active": "305", "total_deceased": "21", "total_recovered": "183", "deceased": "0", "recovered": "0"}, "2021-01-03": {"recovered": "0", "total_confirmed": "509", "active": "305", "total_recovered": "183", "deceased": "0", "confirmed": "0", "total_deceased": "21"}, "2021-01-02": {"total_confirmed": "509", "deceased": "0", "confirmed": "0", "recovered": "0", "active": "305", "total_recovered": "183", "total_deceased": "21"}, "2021-01-01": {"confirmed": "0", "recovered": "0", "total_confirmed": "509", "active": "305", "deceased": "0", "total_recovered": "183", "total_deceased": "21"}, "2020-12-31": {"total_recovered": "183", "deceased": "0", "recovered": "0", "total_confirmed": "509", "confirmed": "0", "active": "305", "total_deceased": "21"}, "2020-12-30": {"confirmed": "0", "deceased": "0", "total_recovered": "183", "active": "305", "total_deceased": "21", "total_confirmed": "509", "recovered": "0"}, "2020-12-29": {"total_deceased": "21", "active": "305", "recovered": "0", "total_recovered": "183", "total_confirmed": "509", "deceased": "0", "confirmed": "0"}, "2020-12-28": {"total_recovered": "183", "total_deceased": "21", "confirmed": "0", "deceased": "0", "total_confirmed": "509", "active": "305", "recovered": "0"}, "2020-12-27": {"total_recovered": "183", "confirmed": "0", "deceased": "0", "active": "305", "total_confirmed": "509", "recovered": "0", "total_deceased": "21"}, "2020-12-26": {"total_confirmed": "509", "total_deceased": "21", "total_recovered": "183", "recovered": "0", "deceased": "0", "confirmed": "0", "active": "305"}, "2020-12-25": {"active": "305", "total_deceased": "21", "deceased": "0", "confirmed": "0", "total_confirmed": "509", "recovered": "0", "total_recovered": "183"}, "2020-12-24": {"total_confirmed": "509", "total_recovered": "183", "confirmed": "0", "deceased": "0", "active": "305", "total_deceased": "21", "recovered": "0"}, "2020-12-23": {"confirmed": "0", "active": "305", "total_deceased": "21", "total_confirmed": "509", "total_recovered": "183", "deceased": "0", "recovered": "0"}, "2020-12-22": {"deceased": "0", "total_deceased": "21", "confirmed": "0", "total_recovered": "183", "total_confirmed": "509", "recovered": "0", "active": "305"}, "2020-12-21": {"deceased": "0", "total_confirmed": "509", "active": "305", "total_deceased": "21", "confirmed": "0", "total_recovered": "183", "recovered": "0"}, "2020-12-20": {"active": "305", "recovered": "0", "confirmed": "0", "total_recovered": "183", "total_deceased": "21", "deceased": "0", "total_confirmed": "509"}, "2020-12-19": {"recovered": "0", "confirmed": "0", "deceased": "0", "total_confirmed": "509", "total_recovered": "183", "total_deceased": "21", "active": "305"}, "2020-12-18": {"total_deceased": "21", "total_recovered": "183", "recovered": "0", "deceased": "0", "confirmed": "0", "total_confirmed": "509", "active": "305"}, "2020-12-17": {"active": "305", "total_recovered": "183", "deceased": "0", "total_deceased": "21", "confirmed": "0", "recovered": "0", "total_confirmed": "509"}, "2020-12-16": {"confirmed": "0", "active": "305", "deceased": "0", "recovered": "0", "total_confirmed": "509", "total_recovered": "183", "total_deceased": "21"}, "2020-12-15": {"total_deceased": "21", "total_recovered": "183", "total_confirmed": "509", "recovered": "0", "confirmed": "0", "deceased": "0", "active": "305"}, "2020-12-14": {"total_recovered": "183", "total_deceased": "21", "confirmed": "0", "deceased": "0", "active": "305", "total_confirmed": "509", "recovered": "0"}, "2020-12-13": {"deceased": "0", "recovered": "0", "confirmed": "0", "total_confirmed": "509", "active": "305", "total_deceased": "21", "total_recovered": "183"}, "2020-12-12": {"total_recovered": "183", "deceased": "0", "confirmed": "0", "total_deceased": "21", "active": "305", "recovered": "0", "total_confirmed": "509"}, "2020-12-11": {"total_confirmed": "509", "recovered": "0", "active": "305", "total_deceased": "21", "deceased": "0", "total_recovered": "183", "confirmed": "0"}, "2020-12-10": {"deceased": "0", "active": "305", "confirmed": "0", "total_recovered": "183", "recovered": "0", "total_confirmed": "509", "total_deceased": "21"}, "2020-12-09": {"active": "305", "total_recovered": "183", "total_deceased": "21", "recovered": "0", "deceased": "0", "total_confirmed": "509", "confirmed": "0"}, "2020-12-08": {"confirmed": "0", "total_deceased": "21", "active": "305", "total_recovered": "183", "deceased": "0", "recovered": "0", "total_confirmed": "509"}, "2020-12-07": {"confirmed": "0", "total_confirmed": "509", "deceased": "0", "active": "305", "total_deceased": "21", "total_recovered": "183", "recovered": "0"}, "2020-12-06": {"total_recovered": "183", "total_confirmed": "509", "deceased": "0", "confirmed": "0", "active": "305", "total_deceased": "21", "recovered": "0"}, "2020-12-05": {"deceased": "0", "recovered": "0", "confirmed": "0", "total_deceased": "21", "total_confirmed": "509", "active": "305", "total_recovered": "183"}, "2020-12-04": {"total_deceased": "21", "active": "305", "total_confirmed": "509", "total_recovered": "183", "confirmed": "0", "recovered": "0", "deceased": "0"}, "2020-12-03": {"total_confirmed": "509", "active": "305", "deceased": "0", "recovered": "0", "total_deceased": "21", "total_recovered": "183", "confirmed": "0"}, "2020-12-02": {"recovered": "0", "confirmed": "0", "active": "305", "total_deceased": "21", "deceased": "0", "total_recovered": "183", "total_confirmed": "509"}, "2020-12-01": {"recovered": "0", "total_recovered": "183", "total_deceased": "21", "deceased": "0", "confirmed": "0", "active": "305", "total_confirmed": "509"}, "2020-11-30": {"total_recovered": "183", "deceased": "0", "recovered": "0", "confirmed": "0", "total_deceased": "21", "active": "305", "total_confirmed": "509"}, "2020-11-29": {"deceased": "0", "total_confirmed": "509", "total_recovered": "183", "active": "305", "confirmed": "0", "recovered": "0", "total_deceased": "21"}, "2020-11-28": {"total_confirmed": "509", "total_recovered": "183", "total_deceased": "21", "recovered": "0", "deceased": "0", "confirmed": "0", "active": "305"}, "2020-11-27": {"recovered": "0", "total_confirmed": "509", "active": "305", "confirmed": "0", "total_deceased": "21", "deceased": "0", "total_recovered": "183"}, "2020-11-26": {"confirmed": "0", "deceased": "0", "total_confirmed": "509", "recovered": "0", "total_deceased": "21", "active": "305", "total_recovered": "183"}, "2020-11-25": {"total_recovered": "183", "deceased": "0", "confirmed": "0", "total_confirmed": "509", "active": "305", "recovered": "0", "total_deceased": "21"}, "2020-11-24": {"confirmed": "0", "total_confirmed": "509", "total_recovered": "183", "recovered": "0", "deceased": "0", "active": "305", "total_deceased": "21"}, "2020-11-23": {"total_confirmed": "509", "deceased": "0", "recovered": "0", "confirmed": "0", "total_deceased": "21", "active": "305", "total_recovered": "183"}, "2020-11-22": {"total_recovered": "183", "deceased": "0", "total_deceased": "21", "active": "305", "confirmed": "0", "total_confirmed": "509", "recovered": "0"}, "2020-11-21": {"confirmed": "0", "total_deceased": "21", "total_confirmed": "509", "recovered": "0", "active": "305", "total_recovered": "183", "deceased": "0"}, "2020-11-20": {"confirmed": "0", "total_deceased": "21", "active": "305", "deceased": "0", "total_recovered": "183", "total_confirmed": "509", "recovered": "0"}, "2020-11-19": {"recovered": "0", "total_recovered": "183", "confirmed": "0", "deceased": "0", "total_deceased": "21", "active": "305", "total_confirmed": "509"}, "2020-11-18": {"total_deceased": "21", "total_confirmed": "509", "confirmed": "0", "recovered": "0", "deceased": "0", "active": "305", "total_recovered": "183"}, "2020-11-17": {"deceased": "0", "total_recovered": "183", "active": "305", "confirmed": "0", "total_deceased": "21", "recovered": "0", "total_confirmed": "509"}, "2020-11-16": {"total_deceased": "21", "total_confirmed": "509", "total_recovered": "183", "confirmed": "0", "recovered": "0", "deceased": "0", "active": "305"}, "2020-11-15": {"total_recovered": "183", "total_confirmed": "509", "total_deceased": "21", "deceased": "0", "recovered": "0", "confirmed": "0", "active": "305"}, "2020-11-14": {"total_recovered": "183", "deceased": "0", "total_confirmed": "509", "active": "305", "recovered": "0", "total_deceased": "21", "confirmed": "0"}, "2020-11-13": {"recovered": "0", "total_confirmed": "509", "total_deceased": "21", "total_recovered": "183", "deceased": "0", "confirmed": "0", "active": "305"}, "2020-11-12": {"total_confirmed": "509", "total_deceased": "21", "confirmed": "0", "active": "305", "deceased": "0", "recovered": "0", "total_recovered": "183"}, "2020-11-11": {"total_recovered": "183", "total_deceased": "21", "active": "305", "deceased": "0", "total_confirmed": "509", "recovered": "0", "confirmed": "0"}, "2020-11-10": {"total_recovered": "183", "deceased": "0", "confirmed": "0", "total_confirmed": "509", "recovered": "0", "active": "305", "total_deceased": "21"}, "2020-11-09": {"total_deceased": "21", "total_recovered": "183", "total_confirmed": "509", "confirmed": "0", "deceased": "0", "active": "305", "recovered": "0"}, "2020-11-08": {"total_deceased": "21", "total_recovered": "183", "deceased": "0", "confirmed": "0", "active": "305", "total_confirmed": "509", "recovered": "0"}, "2020-11-07": {"total_confirmed": "509", "total_deceased": "21", "total_recovered": "183", "deceased": "0", "active": "305", "recovered": "0", "confirmed": "0"}, "2020-11-06": {"confirmed": "0", "total_confirmed": "509", "active": "305", "deceased": "0", "total_deceased": "21", "recovered": "0", "total_recovered": "183"}, "2020-11-05": {"deceased": "0", "recovered": "0", "total_confirmed": "509", "confirmed": "0", "active": "305", "total_recovered": "183", "total_deceased": "21"}, "2020-11-04": {"active": "305", "total_recovered": "183", "total_deceased": "21", "total_confirmed": "509", "recovered": "0", "deceased": "0", "confirmed": "0"}, "2020-11-03": {"total_deceased": "21", "confirmed": "0", "recovered": "0", "active": "305", "total_recovered": "183", "deceased": "0", "total_confirmed": "509"}, "2020-11-02": {"recovered": "0", "deceased": "0", "total_deceased": "21", "confirmed": "0", "total_confirmed": "509", "active": "305", "total_recovered": "183"}, "2020-11-01": {"deceased": "0", "recovered": "0", "active": "305", "total_deceased": "21", "confirmed": "0", "total_recovered": "183", "total_confirmed": "509"}, "2020-10-31": {"deceased": "0", "recovered": "0", "total_confirmed": "509", "confirmed": "0", "active": "305", "total_recovered": "183", "total_deceased": "21"}, "2020-10-30": {"total_recovered": "183", "recovered": "0", "active": "305", "deceased": "0", "total_confirmed": "509", "confirmed": "0", "total_deceased": "21"}, "2020-10-29": {"total_confirmed": "509", "total_deceased": "21", "confirmed": "0", "deceased": "0", "total_recovered": "183", "recovered": "0", "active": "305"}, "2020-10-28": {"total_recovered": "183", "recovered": "0", "total_deceased": "21", "confirmed": "0", "total_confirmed": "509", "active": "305", "deceased": "0"}, "2020-10-27": {"total_recovered": "183", "total_deceased": "21", "total_confirmed": "509", "recovered": "0", "active": "305", "confirmed": "0", "deceased": "0"}, "2020-10-26": {"confirmed": "0", "total_deceased": "21", "total_recovered": "183", "total_confirmed": "509", "deceased": "0", "active": "305", "recovered": "0"}, "2020-10-25": {"recovered": "0", "confirmed": "0", "total_confirmed": "509", "active": "305", "total_recovered": "183", "deceased": "0", "total_deceased": "21"}, "2020-10-24": {"total_confirmed": "509", "confirmed": "0", "deceased": "0", "total_deceased": "21", "recovered": "0", "total_recovered": "183", "active": "305"}, "2020-10-23": {"deceased": "0", "total_recovered": "183", "confirmed": "0", "recovered": "0", "total_confirmed": "509", "total_deceased": "21", "active": "305"}, "2020-10-22": {"total_deceased": "21", "confirmed": "0", "total_recovered": "183", "total_confirmed": "509", "active": "305", "recovered": "0", "deceased": "0"}, "2020-10-21": {"total_recovered": "183", "active": "305", "total_confirmed": "509", "deceased": "0", "total_deceased": "21", "recovered": "0", "confirmed": "0"}, "2020-10-20": {"total_recovered": "183", "deceased": "0", "total_deceased": "21", "total_confirmed": "509", "active": "305", "recovered": "0", "confirmed": "0"}, "2020-10-19": {"recovered": "0", "deceased": "0", "active": "305", "total_confirmed": "509", "confirmed": "0", "total_recovered": "183", "total_deceased": "21"}, "2020-10-18": {"confirmed": "0", "recovered": "0", "deceased": "0", "active": "305", "total_deceased": "21", "total_confirmed": "509", "total_recovered": "183"}, "2020-10-17": {"active": "305", "total_deceased": "21", "confirmed": "0", "total_recovered": "183", "deceased": "0", "recovered": "0", "total_confirmed": "509"}, "2020-10-16": {"total_recovered": "183", "recovered": "0", "total_deceased": "21", "deceased": "0", "active": "305", "confirmed": "0", "total_confirmed": "509"}, "2020-10-15": {"total_deceased": "21", "confirmed": "0", "recovered": "0", "active": "305", "total_confirmed": "509", "deceased": "0", "total_recovered": "183"}, "2020-10-14": {"recovered": "0", "confirmed": "0", "active": "305", "total_confirmed": "509", "total_deceased": "21", "total_recovered": "183", "deceased": "0"}, "2020-10-13": {"total_deceased": "21", "recovered": "0", "total_recovered": "183", "total_confirmed": "509", "deceased": "0", "active": "305", "confirmed": "0"}, "2020-10-12": {"total_recovered": "183", "active": "305", "deceased": "0", "total_deceased": "21", "total_confirmed": "509", "recovered": "0", "confirmed": "0"}, "2020-10-11": {"confirmed": "0", "active": "305", "total_deceased": "21", "deceased": "0", "total_confirmed": "509", "total_recovered": "183", "recovered": "0"}, "2020-10-10": {"total_deceased": "21", "deceased": "0", "total_confirmed": "509", "confirmed": "0", "total_recovered": "183", "recovered": "0", "active": "305"}, "2020-10-09": {"total_recovered": "183", "total_deceased": "21", "active": "305", "recovered": "0", "deceased": "0", "total_confirmed": "509", "confirmed": "0"}, "2020-10-08": {"total_confirmed": "509", "total_recovered": "183", "active": "305", "total_deceased": "21", "deceased": "0", "confirmed": "0", "recovered": "0"}, "2020-10-07": {"total_deceased": "21", "total_confirmed": "509", "recovered": "0", "deceased": "0", "total_recovered": "183", "confirmed": "0", "active": "305"}, "2020-10-06": {"total_confirmed": "509", "recovered": "0", "total_deceased": "21", "confirmed": "0", "total_recovered": "183", "deceased": "0", "active": "305"}, "2020-10-05": {"total_deceased": "21", "recovered": "0", "confirmed": "0", "active": "305", "deceased": "0", "total_recovered": "183", "total_confirmed": "509"}, "2020-10-04": {"confirmed": "0", "total_recovered": "183", "recovered": "0", "active": "305", "total_deceased": "21", "deceased": "0", "total_confirmed": "509"}, "2020-10-03": {"total_deceased": "21", "recovered": "0", "confirmed": "0", "deceased": "0", "total_recovered": "183", "total_confirmed": "509", "active": "305"}, "2020-10-02": {"total_recovered": "183", "total_deceased": "21", "confirmed": "0", "total_confirmed": "509", "deceased": "0", "active": "305", "recovered": "0"}, "2020-10-01": {"total_recovered": "183", "deceased": "0", "recovered": "0", "total_deceased": "21", "confirmed": "0", "total_confirmed": "509", "active": "305"}, "2020-09-30": {"deceased": "0", "total_recovered": "183", "total_deceased": "21", "recovered": "0", "confirmed": "0", "total_confirmed": "509", "active": "305"}, "2020-09-29": {"confirmed": "0", "recovered": "0", "active": "305", "total_confirmed": "509", "total_deceased": "21", "deceased": "0", "total_recovered": "183"}, "2020-09-28": {"total_confirmed": "509", "active": "305", "recovered": "0", "total_deceased": "21", "deceased": "0", "confirmed": "0", "total_recovered": "183"}, "2020-09-27": {"total_confirmed": "509", "confirmed": "0", "active": "305", "deceased": "0", "total_recovered": "183", "recovered": "0", "total_deceased": "21"}, "2020-09-26": {"total_deceased": "21", "total_confirmed": "509", "confirmed": "0", "active": "305", "recovered": "0", "deceased": "0", "total_recovered": "183"}, "2020-09-25": {"total_recovered": "183", "total_confirmed": "509", "active": "305", "recovered": "0", "total_deceased": "21", "deceased": "0", "confirmed": "0"}, "2020-09-24": {"total_recovered": "183", "active": "305", "confirmed": "0", "total_confirmed": "509", "deceased": "0", "total_deceased": "21", "recovered": "0"}, "2020-09-23": {"total_deceased": "21", "total_recovered": "183", "total_confirmed": "509", "deceased": "0", "confirmed": "0", "recovered": "0", "active": "305"}, "2020-09-22": {"deceased": "0", "confirmed": "0", "active": "305", "recovered": "0", "total_recovered": "183", "total_confirmed": "509", "total_deceased": "21"}, "2020-09-21": {"recovered": "0", "active": "305", "total_recovered": "183", "total_confirmed": "509", "total_deceased": "21", "confirmed": "0", "deceased": "0"}, "2020-09-20": {"deceased": "0", "active": "305", "confirmed": "0", "total_deceased": "21", "total_confirmed": "509", "total_recovered": "183", "recovered": "0"}, "2020-09-19": {"total_confirmed": "509", "recovered": "0", "active": "305", "total_deceased": "21", "deceased": "0", "total_recovered": "183", "confirmed": "0"}, "2020-09-18": {"confirmed": "0", "active": "305", "deceased": "0", "total_deceased": "21", "total_confirmed": "509", "total_recovered": "183", "recovered": "0"}, "2020-09-17": {"confirmed": "0", "total_deceased": "21", "deceased": "0", "total_recovered": "183", "active": "305", "total_confirmed": "509", "recovered": "0"}, "2020-09-16": {"total_deceased": "21", "recovered": "0", "deceased": "0", "total_recovered": "183", "confirmed": "0", "total_confirmed": "509", "active": "305"}, "2020-09-15": {"active": "305", "recovered": "0", "total_confirmed": "509", "confirmed": "0", "total_recovered": "183", "deceased": "0", "total_deceased": "21"}, "2020-09-14": {"active": "305", "total_deceased": "21", "confirmed": "0", "deceased": "0", "total_confirmed": "509", "recovered": "0", "total_recovered": "183"}, "2020-09-13": {"total_confirmed": "509", "active": "305", "confirmed": "0", "total_recovered": "183", "recovered": "0", "total_deceased": "21", "deceased": "0"}, "2020-09-12": {"total_deceased": "21", "deceased": "0", "total_recovered": "183", "confirmed": "0", "active": "305", "total_confirmed": "509", "recovered": "0"}, "2020-09-11": {"total_deceased": "21", "total_confirmed": "509", "recovered": "0", "deceased": "0", "active": "305", "total_recovered": "183", "confirmed": "0"}, "2020-09-10": {"confirmed": "0", "deceased": "0", "recovered": "0", "total_deceased": "21", "total_recovered": "183", "total_confirmed": "509", "active": "305"}, "2020-09-09": {"total_confirmed": "509", "deceased": "0", "total_deceased": "21", "active": "305", "confirmed": "0", "total_recovered": "183", "recovered": "0"}, "2020-09-08": {"deceased": "0", "active": "305", "confirmed": "0", "total_deceased": "21", "total_recovered": "183", "total_confirmed": "509", "recovered": "0"}, "2020-09-07": {"deceased": "0", "total_confirmed": "509", "confirmed": "0", "recovered": "0", "total_deceased": "21", "total_recovered": "183", "active": "305"}, "2020-09-06": {"recovered": "0", "total_recovered": "183", "deceased": "0", "total_confirmed": "509", "active": "305", "total_deceased": "21", "confirmed": "0"}, "2020-09-05": {"deceased": "0", "active": "305", "recovered": "0", "confirmed": "0", "total_confirmed": "509", "total_recovered": "183", "total_deceased": "21"}, "2020-09-04": {"confirmed": "0", "active": "305", "recovered": "0", "total_recovered": "183", "total_deceased": "21", "deceased": "0", "total_confirmed": "509"}, "2020-09-03": {"total_confirmed": "509", "recovered": "0", "confirmed": "0", "total_deceased": "21", "active": "305", "deceased": "0", "total_recovered": "183"}, "2020-09-02": {"total_confirmed": "509", "deceased": "0", "confirmed": "0", "active": "305", "total_recovered": "183", "total_deceased": "21", "recovered": "0"}, "2020-09-01": {"total_deceased": "21", "active": "305", "total_recovered": "183", "deceased": "0", "confirmed": "0", "total_confirmed": "509", "recovered": "0"}, "2020-08-31": {"total_confirmed": "509", "deceased": "0", "active": "305", "total_deceased": "21", "recovered": "0", "confirmed": "0", "total_recovered": "183"}, "2020-08-30": {"active": "305", "deceased": "0", "total_deceased": "21", "confirmed": "0", "recovered": "0", "total_recovered": "183", "total_confirmed": "509"}, "2020-08-29": {"recovered": "0", "confirmed": "0", "total_deceased": "21", "active": "305", "total_recovered": "183", "deceased": "0", "total_confirmed": "509"}, "2020-08-28": {"total_deceased": "21", "active": "305", "total_confirmed": "509", "confirmed": "0", "recovered": "0", "total_recovered": "183", "deceased": "0"}, "2020-08-27": {"recovered": "0", "total_recovered": "183", "total_deceased": "21", "deceased": "0", "active": "305", "confirmed": "0", "total_confirmed": "509"}, "2020-08-26": {"recovered": "0", "active": "305", "total_deceased": "21", "total_confirmed": "509", "total_recovered": "183", "deceased": "0", "confirmed": "0"}, "2020-08-25": {"total_recovered": "183", "recovered": "0", "total_deceased": "21", "total_confirmed": "509", "confirmed": "0", "deceased": "0", "active": "305"}, "2020-08-24": {"recovered": "0", "active": "305", "total_recovered": "183", "confirmed": "0", "total_confirmed": "509", "deceased": "0", "total_deceased": "21"}, "2020-08-23": {"active": "305", "confirmed": "0", "total_confirmed": "509", "deceased": "0", "recovered": "0", "total_deceased": "21", "total_recovered": "183"}, "2020-08-22": {"deceased": "0", "confirmed": "0", "recovered": "0", "total_confirmed": "509", "total_deceased": "21", "total_recovered": "183", "active": "305"}, "2020-08-21": {"total_deceased": "21", "recovered": "0", "confirmed": "0", "deceased": "0", "total_confirmed": "509", "total_recovered": "183", "active": "305"}, "2020-08-20": {"recovered": "0", "deceased": "0", "active": "305", "total_confirmed": "509", "total_recovered": "183", "confirmed": "0", "total_deceased": "21"}, "2020-08-19": {"recovered": "0", "total_confirmed": "509", "active": "305", "total_recovered": "183", "total_deceased": "21", "confirmed": "0", "deceased": "0"}, "2020-08-18": {"total_confirmed": "509", "confirmed": "0", "recovered": "0", "total_deceased": "21", "deceased": "0", "active": "305", "total_recovered": "183"}, "2020-08-17": {"confirmed": "0", "total_recovered": "183", "recovered": "0", "active": "305", "deceased": "0", "total_deceased": "21", "total_confirmed": "509"}, "2020-08-16": {"deceased": "0", "recovered": "0", "total_confirmed": "509", "confirmed": "0", "active": "305", "total_recovered": "183", "total_deceased": "21"}, "2020-08-15": {"confirmed": "0", "total_deceased": "21", "deceased": "0", "total_confirmed": "509", "active": "305", "total_recovered": "183", "recovered": "0"}, "2020-08-14": {"deceased": "0", "total_confirmed": "509", "confirmed": "0", "total_recovered": "183", "active": "305", "total_deceased": "21", "recovered": "0"}, "2020-08-13": {"total_recovered": "183", "deceased": "0", "active": "305", "confirmed": "0", "total_deceased": "21", "recovered": "0", "total_confirmed": "509"}, "2020-08-12": {"confirmed": "0", "total_confirmed": "509", "recovered": "0", "total_recovered": "183", "active": "305", "deceased": "0", "total_deceased": "21"}, "2020-08-11": {"total_deceased": "21", "total_confirmed": "509", "total_recovered": "183", "active": "305", "recovered": "0", "confirmed": "0", "deceased": "0"}, "2020-08-10": {"total_confirmed": "509", "total_recovered": "183", "recovered": "0", "total_deceased": "21", "confirmed": "0", "deceased": "0", "active": "305"}, "2020-08-09": {"total_recovered": "183", "active": "305", "total_confirmed": "509", "confirmed": "0", "total_deceased": "21", "deceased": "0", "recovered": "0"}, "2020-08-08": {"confirmed": "0", "recovered": "0", "total_confirmed": "509", "total_deceased": "21", "active": "305", "total_recovered": "183", "deceased": "0"}, "2020-08-07": {"total_recovered": "183", "active": "305", "total_confirmed": "509", "total_deceased": "21", "deceased": "0", "confirmed": "0", "recovered": "0"}, "2020-08-06": {"confirmed": "0", "active": "305", "deceased": "0", "total_confirmed": "509", "total_recovered": "183", "total_deceased": "21", "recovered": "0"}, "2020-08-05": {"deceased": "0", "active": "305", "total_confirmed": "509", "total_deceased": "21", "recovered": "0", "confirmed": "0", "total_recovered": "183"}, "2020-08-04": {"confirmed": "0", "active": "305", "deceased": "0", "total_confirmed": "509", "total_deceased": "21", "recovered": "0", "total_recovered": "183"}, "2020-08-03": {"active": "305", "deceased": "0", "total_recovered": "183", "confirmed": "0", "total_confirmed": "509", "recovered": "0", "total_deceased": "21"}, "2020-08-02": {"deceased": "0", "total_confirmed": "509", "recovered": "0", "total_deceased": "21", "total_recovered": "183", "confirmed": "0", "active": "305"}, "2020-08-01": {"active": "305", "total_deceased": "21", "recovered": "0", "confirmed": "0", "deceased": "0", "total_confirmed": "509", "total_recovered": "183"}, "2020-07-31": {"total_deceased": "21", "deceased": "0", "recovered": "0", "confirmed": "0", "active": "305", "total_recovered": "183", "total_confirmed": "509"}, "2020-07-30": {"total_deceased": "21", "active": "305", "total_confirmed": "509", "confirmed": "0", "total_recovered": "183", "deceased": "0", "recovered": "0"}, "2020-07-29": {"deceased": "0", "active": "305", "recovered": "0", "total_deceased": "21", "total_confirmed": "509", "confirmed": "0", "total_recovered": "183"}, "2020-07-28": {"total_confirmed": "509", "total_deceased": "21", "deceased": "0", "active": "305", "recovered": "0", "confirmed": "0", "total_recovered": "183"}, "2020-07-27": {"total_recovered": "183", "active": "305", "recovered": "0", "total_deceased": "21", "confirmed": "0", "total_confirmed": "509", "deceased": "0"}, "2020-07-26": {"total_recovered": "183", "active": "305", "total_deceased": "21", "recovered": "0", "deceased": "0", "total_confirmed": "509", "confirmed": "0"}, "2020-07-25": {"total_recovered": "183", "deceased": "0", "recovered": "0", "active": "305", "confirmed": "0", "total_deceased": "21", "total_confirmed": "509"}, "2020-07-24": {"deceased": "0", "confirmed": "0", "active": "305", "recovered": "0", "total_recovered": "183", "total_deceased": "21", "total_confirmed": "509"}, "2020-07-23": {"deceased": "0", "confirmed": "0", "active": "305", "total_confirmed": "509", "total_deceased": "21", "recovered": "0", "total_recovered": "183"}, "2020-07-22": {"total_deceased": "21", "recovered": "0", "active": "305", "total_recovered": "183", "confirmed": "0", "deceased": "0", "total_confirmed": "509"}, "2020-07-21": {"recovered": "0", "active": "305", "confirmed": "0", "deceased": "0", "total_recovered": "183", "total_deceased": "21", "total_confirmed": "509"}, "2020-07-20": {"active": "305", "total_deceased": "21", "total_recovered": "183", "total_confirmed": "509", "recovered": "0", "confirmed": "0", "deceased": "0"}, "2020-07-19": {"recovered": "0", "total_recovered": "183", "total_deceased": "21", "total_confirmed": "509", "deceased": "0", "active": "305", "confirmed": "0"}, "2020-07-18": {"active": "305", "confirmed": "0", "deceased": "0", "total_confirmed": "509", "total_recovered": "183", "recovered": "0", "total_deceased": "21"}, "2020-07-17": {"active": "305", "confirmed": "0", "total_recovered": "183", "deceased": "0", "total_deceased": "21", "total_confirmed": "509", "recovered": "0"}, "2020-07-16": {"total_recovered": "183", "confirmed": "0", "total_deceased": "21", "total_confirmed": "509", "active": "305", "recovered": "0", "deceased": "0"}, "2020-07-15": {"total_confirmed": "509", "recovered": "0", "deceased": "0", "total_recovered": "183", "active": "305", "total_deceased": "21", "confirmed": "0"}, "2020-07-14": {"total_deceased": "21", "total_recovered": "183", "recovered": "0", "confirmed": "0", "total_confirmed": "509", "deceased": "0", "active": "305"}, "2020-07-13": {"recovered": "0", "total_confirmed": "509", "active": "305", "total_recovered": "183", "confirmed": "0", "total_deceased": "21", "deceased": "0"}, "2020-07-12": {"confirmed": "0", "total_deceased": "21", "deceased": "0", "active": "305", "total_recovered": "183", "recovered": "0", "total_confirmed": "509"}, "2020-07-11": {"deceased": "0", "total_deceased": "21", "confirmed": "0", "total_confirmed": "509", "active": "305", "total_recovered": "183", "recovered": "0"}, "2020-07-10": {"total_deceased": "21", "deceased": "0", "total_recovered": "183", "confirmed": "0", "active": "305", "total_confirmed": "509", "recovered": "0"}, "2020-07-09": {"deceased": "0", "recovered": "0", "active": "305", "confirmed": "0", "total_recovered": "183", "total_deceased": "21", "total_confirmed": "509"}, "2020-07-08": {"confirmed": "0", "total_deceased": "21", "total_recovered": "183", "active": "305", "total_confirmed": "509", "deceased": "0", "recovered": "0"}, "2020-07-07": {"total_deceased": "21", "total_confirmed": "509", "active": "305", "total_recovered": "183", "deceased": "0", "recovered": "0", "confirmed": "0"}, "2020-07-06": {"recovered": "0", "total_deceased": "21", "confirmed": "0", "total_confirmed": "509", "active": "305", "deceased": "0", "total_recovered": "183"}, "2020-07-05": {"total_deceased": "21", "deceased": "0", "total_recovered": "183", "total_confirmed": "509", "confirmed": "0", "active": "305", "recovered": "0"}, "2020-07-04": {"total_recovered": "183", "active": "305", "total_deceased": "21", "deceased": "0", "confirmed": "0", "total_confirmed": "509", "recovered": "0"}, "2020-07-03": {"total_recovered": "183", "recovered": "0", "confirmed": "0", "total_deceased": "21", "active": "305", "deceased": "0", "total_confirmed": "509"}, "2020-07-02": {"total_recovered": "183", "confirmed": "0", "active": "305", "total_confirmed": "509", "deceased": "0", "total_deceased": "21", "recovered": "0"}, "2020-07-01": {"confirmed": "0", "deceased": "0", "total_confirmed": "509", "total_deceased": "21", "recovered": "0", "active": "305", "total_recovered": "183"}, "2020-06-30": {"total_deceased": "21", "active": "305", "recovered": "0", "total_recovered": "183", "deceased": "0", "total_confirmed": "509", "confirmed": "0"}, "2020-06-29": {"recovered": "0", "total_confirmed": "509", "deceased": "0", "confirmed": "0", "active": "305", "total_deceased": "21", "total_recovered": "183"}, "2020-06-28": {"confirmed": "0", "active": "305", "total_confirmed": "509", "total_deceased": "21", "recovered": "0", "total_recovered": "183", "deceased": "0"}, "2020-06-27": {"total_deceased": "21", "deceased": "0", "recovered": "0", "total_recovered": "183", "total_confirmed": "509", "active": "305", "confirmed": "0"}, "2020-06-26": {"total_confirmed": "509", "active": "305", "deceased": "0", "total_recovered": "183", "recovered": "0", "total_deceased": "21", "confirmed": "0"}, "2020-06-25": {"recovered": "0", "total_recovered": "183", "confirmed": "0", "total_deceased": "21", "total_confirmed": "509", "active": "305", "deceased": "0"}, "2020-06-24": {"total_recovered": "183", "deceased": "0", "active": "305", "total_confirmed": "509", "recovered": "0", "total_deceased": "21", "confirmed": "0"}, "2020-06-23": {"deceased": "0", "active": "305", "recovered": "0", "total_recovered": "183", "total_deceased": "21", "confirmed": "0", "total_confirmed": "509"}, "2020-06-22": {"total_confirmed": "509", "deceased": "0", "recovered": "0", "total_deceased": "21", "total_recovered": "183", "active": "305", "confirmed": "0"}, "2020-06-21": {"deceased": "0", "confirmed": "0", "total_deceased": "21", "active": "305", "recovered": "0", "total_recovered": "183", "total_confirmed": "509"}, "2020-06-20": {"confirmed": "0", "total_deceased": "21", "deceased": "0", "active": "305", "total_confirmed": "509", "total_recovered": "183", "recovered": "0"}, "2020-06-19": {"confirmed": "0", "recovered": "0", "deceased": "0", "total_deceased": "21", "total_recovered": "183", "total_confirmed": "509", "active": "305"}, "2020-06-18": {"confirmed": "0", "total_recovered": "183", "deceased": "0", "active": "305", "total_deceased": "21", "recovered": "0", "total_confirmed": "509"}, "2020-06-17": {"active": "305", "confirmed": "0", "recovered": "0", "total_confirmed": "509", "deceased": "0", "total_recovered": "183", "total_deceased": "21"}, "2020-06-16": {"active": "305", "total_recovered": "183", "recovered": "0", "confirmed": "0", "deceased": "0", "total_deceased": "21", "total_confirmed": "509"}, "2020-06-15": {"total_recovered": "183", "confirmed": "0", "deceased": "0", "recovered": "0", "active": "305", "total_deceased": "21", "total_confirmed": "509"}, "2020-06-14": {"total_confirmed": "509", "total_deceased": "21", "recovered": "0", "deceased": "0", "confirmed": "0", "total_recovered": "183", "active": "305"}, "2020-06-13": {"total_recovered": "183", "confirmed": "0", "deceased": "0", "total_deceased": "21", "recovered": "0", "total_confirmed": "509", "active": "305"}, "2020-06-12": {"total_confirmed": "509", "recovered": "0", "total_recovered": "183", "active": "305", "total_deceased": "21", "deceased": "0", "confirmed": "0"}, "2020-06-11": {"confirmed": "0", "deceased": "0", "total_confirmed": "509", "recovered": "0", "total_recovered": "183", "total_deceased": "21", "active": "305"}, "2020-06-10": {"total_deceased": "21", "total_recovered": "183", "total_confirmed": "509", "recovered": "0", "active": "305", "deceased": "0", "confirmed": "0"}, "2020-06-09": {"total_confirmed": "509", "recovered": "0", "total_recovered": "183", "deceased": "0", "total_deceased": "21", "active": "305", "confirmed": "0"}, "2020-06-08": {"total_recovered": "183", "confirmed": "0", "recovered": "0", "total_confirmed": "509", "active": "305", "deceased": "0", "total_deceased": "21"}, "2020-06-07": {"recovered": "0", "active": "305", "deceased": "0", "total_recovered": "183", "total_deceased": "21", "total_confirmed": "509", "confirmed": "0"}, "2020-06-06": {"recovered": "0", "total_deceased": "21", "total_confirmed": "509", "active": "305", "confirmed": "0", "deceased": "0", "total_recovered": "183"}, "2020-06-05": {"recovered": "0", "total_recovered": "183", "total_confirmed": "509", "active": "305", "deceased": "0", "confirmed": "0", "total_deceased": "21"}, "2020-06-04": {"total_deceased": "21", "total_recovered": "183", "active": "305", "recovered": "0", "total_confirmed": "509", "confirmed": "0", "deceased": "0"}, "2020-06-03": {"total_confirmed": "509", "total_recovered": "183", "recovered": "0", "confirmed": "0", "active": "305", "total_deceased": "21", "deceased": "0"}, "2020-06-02": {"deceased": "0", "total_deceased": "21", "total_confirmed": "509", "confirmed": "0", "recovered": "0", "active": "305", "total_recovered": "183"}, "2020-06-01": {"active": "305", "confirmed": "0", "total_confirmed": "509", "total_deceased": "21", "total_recovered": "183", "recovered": "0", "deceased": "0"}, "2020-05-31": {"deceased": "0", "confirmed": "0", "total_recovered": "183", "active": "305", "recovered": "0", "total_deceased": "21", "total_confirmed": "509"}, "2020-05-30": {"deceased": "0", "active": "305", "recovered": "0", "total_confirmed": "509", "total_deceased": "21", "total_recovered": "183", "confirmed": "0"}, "2020-05-29": {"total_recovered": "183", "confirmed": "0", "active": "305", "recovered": "0", "total_deceased": "21", "total_confirmed": "509", "deceased": "0"}, "2020-05-28": {"confirmed": "0", "total_recovered": "183", "active": "305", "deceased": "0", "total_confirmed": "509", "recovered": "0", "total_deceased": "21"}, "2020-05-27": {"confirmed": "0", "total_deceased": "21", "total_recovered": "183", "deceased": "0", "recovered": "0", "active": "305", "total_confirmed": "509"}, "2020-05-26": {"total_confirmed": "509", "deceased": "0", "recovered": "0", "total_recovered": "183", "total_deceased": "21", "active": "305", "confirmed": "0"}, "2020-05-25": {"recovered": "0", "confirmed": "0", "active": "305", "total_recovered": "183", "total_deceased": "21", "total_confirmed": "509", "deceased": "0"}, "2020-05-24": {"total_deceased": "21", "recovered": "0", "deceased": "0", "confirmed": "0", "total_recovered": "183", "total_confirmed": "509", "active": "305"}, "2020-05-23": {"total_recovered": "183", "deceased": "0", "confirmed": "0", "total_deceased": "21", "recovered": "0", "active": "305", "total_confirmed": "509"}, "2020-05-22": {"deceased": "0", "recovered": "0", "total_confirmed": "509", "active": "305", "confirmed": "0", "total_recovered": "183", "total_deceased": "21"}, "2020-05-21": {"recovered": "0", "total_recovered": "183", "deceased": "0", "total_deceased": "21", "active": "305", "total_confirmed": "509", "confirmed": "0"}, "2020-05-20": {"recovered": "0", "deceased": "0", "active": "305", "total_deceased": "21", "confirmed": "0", "total_recovered": "183", "total_confirmed": "509"}, "2020-05-19": {"total_recovered": "183", "deceased": "0", "confirmed": "0", "total_confirmed": "509", "active": "305", "total_deceased": "21", "recovered": "0"}, "2020-05-18": {"total_deceased": "21", "active": "305", "total_confirmed": "509", "recovered": "0", "deceased": "0", "total_recovered": "183", "confirmed": "0"}, "2020-05-17": {"deceased": "0", "recovered": "0", "active": "305", "total_confirmed": "509", "confirmed": "0", "total_deceased": "21", "total_recovered": "183"}, "2020-05-16": {"recovered": "0", "deceased": "0", "total_deceased": "21", "confirmed": "0", "total_confirmed": "509", "active": "305", "total_recovered": "183"}, "2020-05-15": {"confirmed": "0", "total_confirmed": "509", "recovered": "0", "total_deceased": "21", "deceased": "0", "active": "305", "total_recovered": "183"}, "2020-05-14": {"recovered": "0", "total_confirmed": "509", "deceased": "0", "active": "305", "total_recovered": "183", "confirmed": "0", "total_deceased": "21"}, "2020-05-13": {"total_recovered": "183", "active": "305", "confirmed": "0", "total_deceased": "21", "deceased": "0", "total_confirmed": "509", "recovered": "0"}, "2020-05-12": {"deceased": "0", "confirmed": "0", "total_recovered": "183", "total_confirmed": "509", "total_deceased": "21", "active": "305", "recovered": "0"}, "2020-05-11": {"total_recovered": "183", "deceased": "0", "confirmed": "0", "total_confirmed": "509", "total_deceased": "21", "recovered": "0", "active": "305"}, "2020-05-10": {"recovered": "0", "active": "305", "total_recovered": "183", "confirmed": "0", "total_deceased": "21", "total_confirmed": "509", "deceased": "0"}, "2020-05-09": {"total_recovered": "183", "deceased": "0", "total_deceased": "21", "recovered": "0", "confirmed": "0", "active": "305", "total_confirmed": "509"}, "2020-05-08": {"active": "305", "total_confirmed": "509", "total_deceased": "21", "confirmed": "29", "total_recovered": "183", "recovered": "16", "deceased": "5"}, "2020-05-07": {"deceased": "0", "confirmed": "0", "active": "297", "total_recovered": "167", "recovered": "0", "total_deceased": "16", "total_confirmed": "480"}, "2020-05-06": {"active": "297", "total_deceased": "16", "recovered": "0", "total_confirmed": "480", "confirmed": "0", "total_recovered": "167", "deceased": "0"}, "2020-05-05": {"recovered": "0", "total_recovered": "167", "confirmed": "0", "total_deceased": "16", "deceased": "0", "total_confirmed": "480", "active": "297"}, "2020-05-04": {"total_deceased": "16", "active": "297", "total_confirmed": "480", "total_recovered": "167", "confirmed": "0", "deceased": "0", "recovered": "0"}, "2020-05-03": {"confirmed": "0", "total_confirmed": "480", "recovered": "0", "total_deceased": "16", "total_recovered": "167", "deceased": "0", "active": "297"}, "2020-05-02": {"confirmed": "0", "deceased": "0", "total_deceased": "16", "total_confirmed": "480", "recovered": "0", "total_recovered": "167", "active": "297"}, "2020-05-01": {"active": "297", "deceased": "0", "total_confirmed": "480", "total_deceased": "16", "total_recovered": "167", "confirmed": "0", "recovered": "0"}, "2020-04-30": {"deceased": "0", "total_confirmed": "480", "total_recovered": "167", "recovered": "0", "total_deceased": "16", "confirmed": "0", "active": "297"}, "2020-04-29": {"total_confirmed": "480", "recovered": "119", "total_deceased": "16", "active": "297", "total_recovered": "167", "confirmed": "181", "deceased": "6"}, "2020-04-28": {"deceased": "0", "confirmed": "0", "total_deceased": "10", "total_confirmed": "299", "recovered": "0", "total_recovered": "48", "active": "241"}, "2020-04-27": {"recovered": "0", "total_recovered": "48", "confirmed": "0", "active": "241", "total_deceased": "10", "total_confirmed": "299", "deceased": "0"}, "2020-04-26": {"total_confirmed": "299", "confirmed": "0", "total_deceased": "10", "deceased": "0", "total_recovered": "48", "recovered": "0", "active": "241"}, "2020-04-25": {"total_recovered": "48", "confirmed": "0", "deceased": "0", "total_deceased": "10", "recovered": "0", "total_confirmed": "299", "active": "241"}, "2020-04-24": {"total_confirmed": "299", "deceased": "0", "active": "241", "confirmed": "15", "total_deceased": "10", "recovered": "37", "total_recovered": "48"}, "2020-04-23": {"active": "263", "total_recovered": "11", "deceased": "0", "total_deceased": "10", "confirmed": "0", "total_confirmed": "284", "recovered": "0"}, "2020-04-22": {"total_recovered": "11", "total_confirmed": "284", "active": "263", "total_deceased": "10", "deceased": "0", "confirmed": "30", "recovered": "0"}, "2020-04-21": {"active": "233", "confirmed": "0", "total_confirmed": "254", "total_deceased": "10", "deceased": "0", "recovered": "0", "total_recovered": "11"}, "2020-04-20": {"recovered": "0", "total_deceased": "10", "deceased": "3", "total_recovered": "11", "total_confirmed": "254", "confirmed": "84", "active": "233"}, "2020-04-19": {"total_deceased": "7", "deceased": "2", "total_recovered": "11", "confirmed": "23", "active": "152", "recovered": "0", "total_confirmed": "170"}, "2020-04-18": {"total_recovered": "11", "confirmed": "0", "total_confirmed": "147", "active": "131", "deceased": "0", "total_deceased": "5", "recovered": "0"}, "2020-04-17": {"deceased": "1", "total_confirmed": "147", "total_deceased": "5", "recovered": "0", "total_recovered": "11", "active": "131", "confirmed": "53"}, "2020-04-16": {"recovered": "0", "total_recovered": "11", "deceased": "0", "active": "79", "total_deceased": "4", "confirmed": "6", "total_confirmed": "94"}, "2020-04-15": {"total_confirmed": "88", "total_deceased": "4", "deceased": "1", "recovered": "4", "total_recovered": "11", "confirmed": "35", "active": "73"}, "2020-04-14": {"active": "43", "confirmed": "4", "total_confirmed": "53", "recovered": "0", "deceased": "0", "total_recovered": "7", "total_deceased": "3"}, "2020-04-13": {"total_confirmed": "49", "deceased": "0", "recovered": "2", "active": "39", "confirmed": "17", "total_deceased": "3", "total_recovered": "7"}, "2020-04-12": {"total_confirmed": "32", "deceased": "0", "recovered": "0", "total_deceased": "3", "total_recovered": "5", "confirmed": "0", "active": "24"}, "2020-04-11": {"active": "24", "total_deceased": "3", "total_recovered": "5", "recovered": "0", "confirmed": "0", "total_confirmed": "32", "deceased": "0"}, "2020-04-10": {"deceased": "2", "recovered": "0", "total_recovered": "5", "total_deceased": "3", "confirmed": "7", "active": "24", "total_confirmed": "32"}, "2020-04-09": {"total_confirmed": "25", "confirmed": "0", "total_recovered": "5", "total_deceased": "1", "recovered": "0", "deceased": "0", "active": "19"}, "2020-04-08": {"total_deceased": "1", "total_confirmed": "25", "deceased": "0", "total_recovered": "5", "recovered": "0", "confirmed": "1", "active": "19"}, "2020-04-07": {"total_deceased": "1", "active": "18", "confirmed": "0", "deceased": "0", "total_confirmed": "24", "total_recovered": "5", "recovered": "2"}, "2020-04-06": {"recovered": "0", "total_confirmed": "24", "confirmed": "2", "deceased": "0", "total_deceased": "1", "total_recovered": "3", "active": "20"}, "2020-04-05": {"total_confirmed": "22", "total_deceased": "1", "confirmed": "2", "recovered": "0", "active": "18", "total_recovered": "3", "deceased": "0"}, "2020-04-04": {"total_confirmed": "20", "deceased": "0", "total_deceased": "1", "active": "16", "recovered": "0", "total_recovered": "3", "confirmed": "0"}, "2020-04-03": {"recovered": "1", "active": "16", "confirmed": "0", "deceased": "0", "total_deceased": "1", "total_recovered": "3", "total_confirmed": "20"}, "2020-04-02": {"deceased": "0", "total_confirmed": "20", "recovered": "1", "confirmed": "0", "active": "17", "total_deceased": "1", "total_recovered": "2"}, "2020-04-01": {"total_deceased": "1", "total_confirmed": "20", "recovered": "0", "total_recovered": "1", "confirmed": "1", "deceased": "0", "active": "18"}, "2020-03-31": {"confirmed": "0", "active": "17", "total_recovered": "1", "total_confirmed": "19", "total_deceased": "1", "deceased": "1", "recovered": "0"}, "2020-03-30": {"deceased": "0", "total_deceased": "0", "recovered": "0", "confirmed": "5", "total_confirmed": "19", "total_recovered": "1", "active": "18"}, "2020-03-29": {"active": "13", "total_confirmed": "14", "total_deceased": "0", "confirmed": "0", "total_recovered": "1", "deceased": "0", "recovered": "0"}, "2020-03-28": {"confirmed": "1", "recovered": "0", "total_deceased": "0", "deceased": "0", "active": "13", "total_confirmed": "14", "total_recovered": "1"}, "2020-03-27": {"total_confirmed": "13", "recovered": "1", "confirmed": "0", "total_recovered": "1", "total_deceased": "0", "deceased": "0", "active": "12"}, "2020-03-26": {"total_recovered": "0", "recovered": "0", "total_deceased": "0", "deceased": "0", "active": "13", "total_confirmed": "13", "confirmed": "1"}, "2020-03-25": {"total_deceased": "0", "total_confirmed": "12", "deceased": "0", "confirmed": "0", "total_recovered": "0", "active": "12", "recovered": "0"}, "2020-03-24": {"total_confirmed": "12", "recovered": "0", "active": "12", "total_recovered": "0", "confirmed": "0", "deceased": "0", "total_deceased": "0"}, "2020-03-23": {"deceased": "0", "recovered": "0", "active": "12", "total_confirmed": "12", "confirmed": "0", "total_recovered": "0", "total_deceased": "0"}, "2020-03-22": {"total_deceased": "0", "active": "12", "confirmed": "6", "recovered": "0", "deceased": "0", "total_confirmed": "12", "total_recovered": "0"}, "2020-03-21": {"total_recovered": "0", "deceased": "0", "total_confirmed": "6", "active": "6", "recovered": "0", "total_deceased": "0", "confirmed": "0"}, "2020-03-20": {"active": "6", "deceased": "0", "total_recovered": "0", "total_deceased": "0", "recovered": "0", "confirmed": "0", "total_confirmed": "6"}, "2020-03-19": {"total_deceased": "0", "confirmed": "3", "total_recovered": "0", "total_confirmed": "6", "active": "6", "deceased": "0", "recovered": "0"}, "2020-03-18": {"total_confirmed": "3", "total_recovered": "0", "recovered": "0", "confirmed": "2", "deceased": "0", "total_deceased": "0", "active": "3"}, "2020-03-17": {"confirmed": "0", "total_deceased": "0", "total_confirmed": "1", "active": "1", "total_recovered": "0", "recovered": "0", "deceased": "0"}, "2020-03-16": {"deceased": "0", "active": "1", "confirmed": "1", "total_recovered": "0", "total_confirmed": "1", "recovered": "0", "total_deceased": "0"}, "2020-03-15": {"deceased": "0", "active": "0", "total_confirmed": "0", "recovered": "0", "confirmed": "0", "total_deceased": "0", "total_recovered": "0"}, "2020-03-14": {"deceased": "0", "active": "0", "total_deceased": "0", "recovered": "0", "total_confirmed": "0", "total_recovered": "0", "confirmed": "0"}, "2020-03-13": {"confirmed": "0", "deceased": "0", "recovered": "0", "total_confirmed": "0", "active": "0", "total_recovered": "0", "total_deceased": "0"}, "2020-03-12": {"total_deceased": "0", "recovered": "0", "total_recovered": "0", "confirmed": "0", "deceased": "0", "total_confirmed": "0", "active": "0"}, "2020-03-11": {"deceased": "0", "active": "0", "total_confirmed": "0", "total_recovered": "0", "recovered": "0", "total_deceased": "0", "confirmed": "0"}, "2020-03-10": {"total_confirmed": "0", "total_deceased": "0", "recovered": "0", "active": "0", "total_recovered": "0", "confirmed": "0", "deceased": "0"}, "2020-03-09": {"total_deceased": "0", "deceased": "0", "recovered": "0", "total_confirmed": "0", "total_recovered": "0", "confirmed": "0", "active": "0"}, "2020-03-08": {"active": "0", "confirmed": "0", "total_confirmed": "0", "total_recovered": "0", "total_deceased": "0", "recovered": "0", "deceased": "0"}, "2020-03-07": {"total_confirmed": "0", "active": "0", "total_deceased": "0", "total_recovered": "0", "deceased": "0", "confirmed": "0", "recovered": "0"}, "2020-03-06": {"total_recovered": "0", "total_deceased": "0", "active": "0", "recovered": "0", "deceased": "0", "confirmed": "0", "total_confirmed": "0"}, "2020-03-05": {"total_recovered": "0", "confirmed": "0", "deceased": "0", "recovered": "0", "total_deceased": "0", "active": "0", "total_confirmed": "0"}, "2020-03-04": {"deceased": "0", "total_confirmed": "0", "total_deceased": "0", "active": "0", "recovered": "0", "confirmed": "0", "total_recovered": "0"}, "2020-03-03": {"total_recovered": "0", "confirmed": "0", "deceased": "0", "active": "0", "recovered": "0", "total_deceased": "0", "total_confirmed": "0"}, "2020-03-02": {"active": "0", "deceased": "0", "total_recovered": "0", "confirmed": "0", "recovered": "0", "total_confirmed": "0", "total_deceased": "0"}, "2020-03-01": {"total_deceased": "0", "active": "0", "total_confirmed": "0", "recovered": "0", "deceased": "0", "total_recovered": "0", "confirmed": "0"}, "2020-02-29": {"confirmed": "0", "total_confirmed": "0", "total_recovered": "0", "total_deceased": "0", "deceased": "0", "active": "0", "recovered": "0"}, "2020-02-28": {"active": "0", "confirmed": "0", "total_recovered": "0", "recovered": "0", "total_confirmed": "0", "total_deceased": "0", "deceased": "0"}, "2020-02-27": {"active": "0", "deceased": "0", "total_confirmed": "0", "confirmed": "0", "total_deceased": "0", "recovered": "0", "total_recovered": "0"}, "2020-02-26": {"recovered": "0", "total_confirmed": "0", "active": "0", "confirmed": "0", "total_deceased": "0", "deceased": "0", "total_recovered": "0"}, "2020-02-25": {"total_recovered": "0", "recovered": "0", "deceased": "0", "total_confirmed": "0", "total_deceased": "0", "confirmed": "0", "active": "0"}, "2020-02-24": {"confirmed": "0", "total_confirmed": "0", "recovered": "0", "total_deceased": "0", "active": "0", "total_recovered": "0", "deceased": "0"}, "2020-02-23": {"recovered": "0", "total_confirmed": "0", "total_recovered": "0", "active": "0", "total_deceased": "0", "deceased": "0", "confirmed": "0"}, "2020-02-22": {"total_deceased": "0", "total_confirmed": "0", "total_recovered": "0", "deceased": "0", "active": "0", "recovered": "0", "confirmed": "0"}, "2020-02-21": {"deceased": "0", "total_confirmed": "0", "recovered": "0", "total_recovered": "0", "total_deceased": "0", "active": "0", "confirmed": "0"}, "2020-02-20": {"total_deceased": "0", "total_recovered": "0", "total_confirmed": "0", "recovered": "0", "active": "0", "deceased": "0", "confirmed": "0"}, "2020-02-19": {"total_deceased": "0", "confirmed": "0", "total_confirmed": "0", "recovered": "0", "active": "0", "total_recovered": "0", "deceased": "0"}, "2020-02-18": {"recovered": "0", "deceased": "0", "confirmed": "0", "total_recovered": "0", "total_confirmed": "0", "total_deceased": "0", "active": "0"}, "2020-02-17": {"total_recovered": "0", "deceased": "0", "active": "0", "recovered": "0", "total_deceased": "0", "total_confirmed": "0", "confirmed": "0"}, "2020-02-16": {"deceased": "0", "total_deceased": "0", "recovered": "0", "active": "0", "total_recovered": "0", "total_confirmed": "0", "confirmed": "0"}, "2020-02-15": {"recovered": "0", "total_recovered": "0", "confirmed": "0", "total_confirmed": "0", "active": "0", "deceased": "0", "total_deceased": "0"}, "2020-02-14": {"recovered": "0", "total_confirmed": "0", "active": "0", "confirmed": "0", "total_recovered": "0", "deceased": "0", "total_deceased": "0"}, "2020-02-13": {"total_confirmed": "0", "recovered": "0", "total_recovered": "0", "active": "0", "total_deceased": "0", "confirmed": "0", "deceased": "0"}, "2020-02-12": {"deceased": "0", "confirmed": "0", "recovered": "0", "total_confirmed": "0", "active": "0", "total_recovered": "0", "total_deceased": "0"}, "2020-02-11": {"deceased": "0", "confirmed": "0", "total_recovered": "0", "active": "0", "total_confirmed": "0", "recovered": "0", "total_deceased": "0"}, "2020-02-10": {"total_confirmed": "0", "recovered": "0", "confirmed": "0", "total_recovered": "0", "total_deceased": "0", "active": "0", "deceased": "0"}, "2020-02-09": {"total_recovered": "0", "confirmed": "0", "deceased": "0", "total_confirmed": "0", "total_deceased": "0", "active": "0", "recovered": "0"}, "2020-02-08": {"recovered": "0", "confirmed": "0", "total_confirmed": "0", "deceased": "0", "total_deceased": "0", "active": "0", "total_recovered": "0"}, "2020-02-07": {"total_recovered": "0", "total_deceased": "0", "confirmed": "0", "total_confirmed": "0", "deceased": "0", "recovered": "0", "active": "0"}, "2020-02-06": {"active": "0", "total_confirmed": "0", "deceased": "0", "recovered": "0", "total_recovered": "0", "confirmed": "0", "total_deceased": "0"}, "2020-02-05": {"active": "0", "total_recovered": "0", "deceased": "0", "total_deceased": "0", "recovered": "0", "total_confirmed": "0", "confirmed": "0"}, "2020-02-04": {"active": "0", "confirmed": "0", "recovered": "0", "total_recovered": "0", "total_confirmed": "0", "total_deceased": "0", "deceased": "0"}, "2020-02-03": {"total_recovered": "0", "total_confirmed": "0", "recovered": "0", "active": "0", "confirmed": "0", "deceased": "0", "total_deceased": "0"}, "2020-02-02": {"total_deceased": "0", "total_confirmed": "0", "total_recovered": "0", "confirmed": "0", "active": "0", "recovered": "0", "deceased": "0"}, "2020-02-01": {"total_recovered": "0", "confirmed": "0", "deceased": "0", "recovered": "0", "total_deceased": "0", "active": "0", "total_confirmed": "0"}, "2020-01-31": {"total_recovered": "0", "total_confirmed": "0", "deceased": "0", "active": "0", "recovered": "0", "confirmed": "0", "total_deceased": "0"}, "2020-01-30": {"total_recovered": "0", "recovered": "0", "deceased": "0", "total_deceased": "0", "confirmed": "0", "active": "0", "total_confirmed": "0"}, "2020-01-29": {"total_recovered": "0", "total_confirmed": "0", "confirmed": "0", "active": "0", "total_deceased": "0", "deceased": "0", "recovered": "0"}, "2020-01-28": {"confirmed": "0", "total_deceased": "0", "recovered": "0", "active": "0", "total_recovered": "0", "deceased": "0", "total_confirmed": "0"}, "2020-01-27": {"deceased": "0", "total_confirmed": "0", "total_recovered": "0", "recovered": "0", "active": "0", "total_deceased": "0", "confirmed": "0"}, "2020-01-26": {"total_confirmed": "0", "total_deceased": "0", "active": "0", "recovered": "0", "deceased": "0", "confirmed": "0", "total_recovered": "0"}, "2020-01-25": {"total_recovered": "0", "total_deceased": "0", "recovered": "0", "total_confirmed": "0", "confirmed": "0", "deceased": "0", "active": "0"}, "2020-01-24": {"total_deceased": "0", "total_recovered": "0", "deceased": "0", "active": "0", "recovered": "0", "confirmed": "0", "total_confirmed": "0"}, "2020-01-23": {"active": "0", "total_recovered": "0", "total_confirmed": "0", "deceased": "0", "confirmed": "0", "total_deceased": "0", "recovered": "0"}, "2020-01-22": {"deceased": "0", "total_confirmed": "0", "recovered": "0", "confirmed": "0", "total_deceased": "0", "total_recovered": "0", "active": "0"}}